osmeterium/__init__.py
osmeterium/run_command.py
osmeterium-0.0.3.dist-info/METADATA
osmeterium-0.0.3.dist-info/WHEEL
osmeterium-0.0.3.dist-info/top_level.txt
osmeterium-0.0.3.dist-info/RECORD
