Metadata-Version: 2.1
Name: osmeterium
Version: 0.0.3
Summary: A wrapper for subprocess popen
Home-page: https://github.com/MapColonies/osmeterium
Author: MapColonies
Author-email: mapcolonies@gmail.com
License: UNKNOWN
Platform: UNKNOWN
Classifier: Programming Language :: Python :: 3
Classifier: License :: OSI Approved :: MIT License
Classifier: Operating System :: OS Independent
Requires-Python: >=3.6
